GoTurn/Model.py
GoTurn/__init__.py
goturn_pytorch-1.0.dist-info/LICENSE
goturn_pytorch-1.0.dist-info/METADATA
goturn_pytorch-1.0.dist-info/WHEEL
goturn_pytorch-1.0.dist-info/top_level.txt
goturn_pytorch-1.0.dist-info/RECORD
