Metadata-Version: 2.1
Name: goturn-pytorch
Version: 1.0
Summary: A PyTorch port of GOTURN tracker
Home-page: https://github.com/aakaashjois/PyTorch-GOTURN
Author: Aakaash Jois
Author-email: aakaashjois@gmail.com
License: MIT
Keywords: machine-learning,pytorch,deep-learning
Platform: UNKNOWN
Classifier: Development Status :: 5 - Production/Stable
Classifier: License :: OSI Approved :: MIT License
Classifier: Programming Language :: Python :: 3.7
Classifier: Topic :: Scientific/Engineering :: Artificial Intelligence
Requires-Dist: torch
